golang
oracle
