Metadata-Version: 1.2
Name: oracle-eth
Version: 0.0.20
Summary: 这是一个event监听程序，用于数据交换
Home-page: https://gitlab.hard-chain.cn/cport/oracle
Author: yuyongpeng
Author-email: yuyongpeng@hotmail.com
License: MIT License
